truvity_sdk/__init__.py
truvity_sdk/client.py
truvity_sdk/core/__init__.py
truvity_sdk/core/api_error.py
truvity_sdk/core/client_wrapper.py
truvity_sdk/core/datetime_utils.py
truvity_sdk/core/file.py
truvity_sdk/core/http_client.py
truvity_sdk/core/jsonable_encoder.py
truvity_sdk/core/remove_none_from_dict.py
truvity_sdk/core/request_options.py
truvity_sdk/environment.py
truvity_sdk/errors/__init__.py
truvity_sdk/errors/bad_request_error.py
truvity_sdk/errors/forbidden_error.py
truvity_sdk/errors/internal_server_error.py
truvity_sdk/errors/not_found_error.py
truvity_sdk/errors/unauthorized_error.py
truvity_sdk/py.typed
truvity_sdk/resources/__init__.py
truvity_sdk/resources/owners/__init__.py
truvity_sdk/resources/owners/client.py
truvity_sdk/resources/pets/__init__.py
truvity_sdk/resources/pets/client.py
truvity_sdk/types/__init__.py
truvity_sdk/types/annotation_value.py
truvity_sdk/types/annotations.py
truvity_sdk/types/bad_request_error_body.py
truvity_sdk/types/blob_id.py
truvity_sdk/types/checksum.py
truvity_sdk/types/checksum_algorithm.py
truvity_sdk/types/checksum_crc_32.py
truvity_sdk/types/checksum_crc_32_c.py
truvity_sdk/types/checksum_sha_1.py
truvity_sdk/types/checksum_sha_256.py
truvity_sdk/types/content_type.py
truvity_sdk/types/download.py
truvity_sdk/types/e_tag.py
truvity_sdk/types/filter_id.py
truvity_sdk/types/filter_id_equal.py
truvity_sdk/types/filter_id_in.py
truvity_sdk/types/filter_id_not_equal.py
truvity_sdk/types/filter_id_not_in.py
truvity_sdk/types/filter_integer.py
truvity_sdk/types/filter_integer_between.py
truvity_sdk/types/filter_integer_equal.py
truvity_sdk/types/filter_integer_greater_than.py
truvity_sdk/types/filter_integer_greater_than_or_equal.py
truvity_sdk/types/filter_integer_less_than.py
truvity_sdk/types/filter_integer_less_than_or_equal.py
truvity_sdk/types/filter_integer_not_equal.py
truvity_sdk/types/filter_string.py
truvity_sdk/types/filter_string_equal.py
truvity_sdk/types/filter_string_not_equal.py
truvity_sdk-0.0.1.dist-info/METADATA
truvity_sdk-0.0.1.dist-info/WHEEL
truvity_sdk-0.0.1.dist-info/RECORD
